src/vhdl/PR2/ADDER.vhdl
library ieee;
use ieee.std_logic_1164.all;
use ieee.numeric_std.all;

entity ADDER is
generic( n: integer := 32 );
port (
	A, B: in std_logic_vector(n-1 downto 0);
	R: out std_logic_vector(n-1 downto 0)
);
end entity;

architecture arch of ADDER is begin

	R <= std_logic_vector(unsigned(A) + unsigned(B));

end architecture;

src/vhdl/PR2/TB_ADDER.vhdl
-- TIME=40ns
library ieee;
use ieee.std_logic_1164.all;

entity TB_ADDER is end entity;

architecture behavior of TB_ADDER is

	component ADDER is
	generic( n: integer := 32 );
	port (
		A, B: in std_logic_vector(n-1 downto 0);
		R: out std_logic_vector(n-1 downto 0)
	);
	end component;

	signal a, b, r : std_logic_vector(31 downto 0);

begin

	uut: ADDER
	generic map(n => 32)
	port map(
		A 	=> a,
		B 	=> b,
		R 	=> r
	);

	Stimuli: process begin
	
		a <= x"00000000";
		b <= x"00000001";
		wait for 10 ns;

		a <= x"00000010";
		b <= x"00001001";
		wait for 10 ns;

		a <= x"00001000";
		b <= x"00000001";
		wait for 10 ns;

		a <= x"00001000";
		b <= x"00000111";
		wait for 10 ns;

	end process;

end architecture;

src/vhdl/PR2/vcds/ADDER.vcd
$date
  Tue Jun 14 11:48:34 2022
$end
$version
  GHDL v0
$end
$timescale
  1 fs
$end
$scope module standard $end
$upscope $end
$scope module std_logic_1164 $end
$upscope $end
$scope module numeric_std $end
$upscope $end
$scope module tb_adder $end
$var reg 32 ! a[31:0] $end
$var reg 32 " b[31:0] $end
$var reg 32 # r[31:0] $end
$scope module uut $end
$var reg 32 $ a[31:0] $end
$var reg 32 % b[31:0] $end
$var reg 32 & r[31:0] $end
$upscope $end
$upscope $end
$enddefinitions $end
#0
b00000000000000000000000000000000 !
b00000000000000000000000000000001 "
b00000000000000000000000000000001 #
b00000000000000000000000000000000 $
b00000000000000000000000000000001 %
b00000000000000000000000000000001 &
#10000000
b00000000000000000000000000010000 !
b00000000000000000001000000000001 "
b00000000000000000001000000010001 #
b00000000000000000000000000010000 $
b00000000000000000001000000000001 %
b00000000000000000001000000010001 &
#20000000
b00000000000000000001000000000000 !
b00000000000000000000000000000001 "
b00000000000000000001000000000001 #
b00000000000000000001000000000000 $
b00000000000000000000000000000001 %
b00000000000000000001000000000001 &
#30000000
b00000000000000000000000100010001 "
b00000000000000000001000100010001 #
b00000000000000000000000100010001 %
b00000000000000000001000100010001 &
#40000000
b00000000000000000000000000000000 !
b00000000000000000000000000000001 "
b00000000000000000000000000000001 #
b00000000000000000000000000000000 $
b00000000000000000000000000000001 %
b00000000000000000000000000000001 &
#50000000
b00000000000000000000000000010000 !
b00000000000000000001000000000001 "
b00000000000000000001000000010001 #
b00000000000000000000000000010000 $
b00000000000000000001000000000001 %
b00000000000000000001000000010001 &
#60000000
b00000000000000000001000000000000 !
b00000000000000000000000000000001 "
b00000000000000000001000000000001 #
b00000000000000000001000000000000 $
b00000000000000000000000000000001 %
b00000000000000000001000000000001 &
#70000000
b00000000000000000000000100010001 "
b00000000000000000001000100010001 #
b00000000000000000000000100010001 %
b00000000000000000001000100010001 &
#80000000
b00000000000000000000000000000000 !
b00000000000000000000000000000001 "
b00000000000000000000000000000001 #
b00000000000000000000000000000000 $
b00000000000000000000000000000001 %
b00000000000000000000000000000001 &
#90000000
b00000000000000000000000000010000 !
b00000000000000000001000000000001 "
b00000000000000000001000000010001 #
b00000000000000000000000000010000 $
b00000000000000000001000000000001 %
b00000000000000000001000000010001 &
#100000000
b00000000000000000001000000000000 !
b00000000000000000000000000000001 "
b00000000000000000001000000000001 #
b00000000000000000001000000000000 $
b00000000000000000000000000000001 %
b00000000000000000001000000000001 &
#110000000
b00000000000000000000000100010001 "
b00000000000000000001000100010001 #
b00000000000000000000000100010001 %
b00000000000000000001000100010001 &
#120000000
b00000000000000000000000000000000 !
b00000000000000000000000000000001 "
b00000000000000000000000000000001 #
b00000000000000000000000000000000 $
b00000000000000000000000000000001 %
b00000000000000000000000000000001 &
#130000000
b00000000000000000000000000010000 !
b00000000000000000001000000000001 "
b00000000000000000001000000010001 #
b00000000000000000000000000010000 $
b00000000000000000001000000000001 %
b00000000000000000001000000010001 &
#140000000
b00000000000000000001000000000000 !
b00000000000000000000000000000001 "
b00000000000000000001000000000001 #
b00000000000000000001000000000000 $
b00000000000000000000000000000001 %
b00000000000000000001000000000001 &
#150000000
b00000000000000000000000100010001 "
b00000000000000000001000100010001 #
b00000000000000000000000100010001 %
b00000000000000000001000100010001 &
#160000000
b00000000000000000000000000000000 !
b00000000000000000000000000000001 "
b00000000000000000000000000000001 #
b00000000000000000000000000000000 $
b00000000000000000000000000000001 %
b00000000000000000000000000000001 &
#170000000
b00000000000000000000000000010000 !
b00000000000000000001000000000001 "
b00000000000000000001000000010001 #
b00000000000000000000000000010000 $
b00000000000000000001000000000001 %
b00000000000000000001000000010001 &
#180000000
b00000000000000000001000000000000 !
b00000000000000000000000000000001 "
b00000000000000000001000000000001 #
b00000000000000000001000000000000 $
b00000000000000000000000000000001 %
b00000000000000000001000000000001 &
#190000000
b00000000000000000000000100010001 "
b00000000000000000001000100010001 #
b00000000000000000000000100010001 %
b00000000000000000001000100010001 &
#200000000
b00000000000000000000000000000000 !
b00000000000000000000000000000001 "
b00000000000000000000000000000001 #
b00000000000000000000000000000000 $
b00000000000000000000000000000001 %
b00000000000000000000000000000001 &
#210000000
b00000000000000000000000000010000 !
b00000000000000000001000000000001 "
b00000000000000000001000000010001 #
b00000000000000000000000000010000 $
b00000000000000000001000000000001 %
b00000000000000000001000000010001 &
#220000000
b00000000000000000001000000000000 !
b00000000000000000000000000000001 "
b00000000000000000001000000000001 #
b00000000000000000001000000000000 $
b00000000000000000000000000000001 %
b00000000000000000001000000000001 &
#230000000
b00000000000000000000000100010001 "
b00000000000000000001000100010001 #
b00000000000000000000000100010001 %
b00000000000000000001000100010001 &
#240000000
b00000000000000000000000000000000 !
b00000000000000000000000000000001 "
b00000000000000000000000000000001 #
b00000000000000000000000000000000 $
b00000000000000000000000000000001 %
b00000000000000000000000000000001 &
#250000000
b00000000000000000000000000010000 !
b00000000000000000001000000000001 "
b00000000000000000001000000010001 #
b00000000000000000000000000010000 $
b00000000000000000001000000000001 %
b00000000000000000001000000010001 &
#260000000
b00000000000000000001000000000000 !
b00000000000000000000000000000001 "
b00000000000000000001000000000001 #
b00000000000000000001000000000000 $
b00000000000000000000000000000001 %
b00000000000000000001000000000001 &
#270000000
b00000000000000000000000100010001 "
b00000000000000000001000100010001 #
b00000000000000000000000100010001 %
b00000000000000000001000100010001 &
#280000000
b00000000000000000000000000000000 !
b00000000000000000000000000000001 "
b00000000000000000000000000000001 #
b00000000000000000000000000000000 $
b00000000000000000000000000000001 %
b00000000000000000000000000000001 &
#290000000
b00000000000000000000000000010000 !
b00000000000000000001000000000001 "
b00000000000000000001000000010001 #
b00000000000000000000000000010000 $
b00000000000000000001000000000001 %
b00000000000000000001000000010001 &
#300000000
b00000000000000000001000000000000 !
b00000000000000000000000000000001 "
b00000000000000000001000000000001 #
b00000000000000000001000000000000 $
b00000000000000000000000000000001 %
b00000000000000000001000000000001 &
#310000000
b00000000000000000000000100010001 "
b00000000000000000001000100010001 #
b00000000000000000000000100010001 %
b00000000000000000001000100010001 &
#320000000
b00000000000000000000000000000000 !
b00000000000000000000000000000001 "
b00000000000000000000000000000001 #
b00000000000000000000000000000000 $
b00000000000000000000000000000001 %
b00000000000000000000000000000001 &
#330000000
b00000000000000000000000000010000 !
b00000000000000000001000000000001 "
b00000000000000000001000000010001 #
b00000000000000000000000000010000 $
b00000000000000000001000000000001 %
b00000000000000000001000000010001 &
#340000000
b00000000000000000001000000000000 !
b00000000000000000000000000000001 "
b00000000000000000001000000000001 #
b00000000000000000001000000000000 $
b00000000000000000000000000000001 %
b00000000000000000001000000000001 &
#350000000
b00000000000000000000000100010001 "
b00000000000000000001000100010001 #
b00000000000000000000000100010001 %
b00000000000000000001000100010001 &
#360000000
b00000000000000000000000000000000 !
b00000000000000000000000000000001 "
b00000000000000000000000000000001 #
b00000000000000000000000000000000 $
b00000000000000000000000000000001 %
b00000000000000000000000000000001 &
#370000000
b00000000000000000000000000010000 !
b00000000000000000001000000000001 "
b00000000000000000001000000010001 #
b00000000000000000000000000010000 $
b00000000000000000001000000000001 %
b00000000000000000001000000010001 &
#380000000
b00000000000000000001000000000000 !
b00000000000000000000000000000001 "
b00000000000000000001000000000001 #
b00000000000000000001000000000000 $
b00000000000000000000000000000001 %
b00000000000000000001000000000001 &
#390000000
b00000000000000000000000100010001 "
b00000000000000000001000100010001 #
b00000000000000000000000100010001 %
b00000000000000000001000100010001 &
#400000000
b00000000000000000000000000000000 !
b00000000000000000000000000000001 "
b00000000000000000000000000000001 #
b00000000000000000000000000000000 $
b00000000000000000000000000000001 %
b00000000000000000000000000000001 &
#410000000
b00000000000000000000000000010000 !
b00000000000000000001000000000001 "
b00000000000000000001000000010001 #
b00000000000000000000000000010000 $
b00000000000000000001000000000001 %
b00000000000000000001000000010001 &
#420000000
b00000000000000000001000000000000 !
b00000000000000000000000000000001 "
b00000000000000000001000000000001 #
b00000000000000000001000000000000 $
b00000000000000000000000000000001 %
b00000000000000000001000000000001 &
#430000000
b00000000000000000000000100010001 "
b00000000000000000001000100010001 #
b00000000000000000000000100010001 %
b00000000000000000001000100010001 &
#440000000
b00000000000000000000000000000000 !
b00000000000000000000000000000001 "
b00000000000000000000000000000001 #
b00000000000000000000000000000000 $
b00000000000000000000000000000001 %
b00000000000000000000000000000001 &
#450000000
b00000000000000000000000000010000 !
b00000000000000000001000000000001 "
b00000000000000000001000000010001 #
b00000000000000000000000000010000 $
b00000000000000000001000000000001 %
b00000000000000000001000000010001 &
#460000000
b00000000000000000001000000000000 !
b00000000000000000000000000000001 "
b00000000000000000001000000000001 #
b00000000000000000001000000000000 $
b00000000000000000000000000000001 %
b00000000000000000001000000000001 &
#470000000
b00000000000000000000000100010001 "
b00000000000000000001000100010001 #
b00000000000000000000000100010001 %
b00000000000000000001000100010001 &
#480000000
b00000000000000000000000000000000 !
b00000000000000000000000000000001 "
b00000000000000000000000000000001 #
b00000000000000000000000000000000 $
b00000000000000000000000000000001 %
b00000000000000000000000000000001 &
#490000000
b00000000000000000000000000010000 !
b00000000000000000001000000000001 "
b00000000000000000001000000010001 #
b00000000000000000000000000010000 $
b00000000000000000001000000000001 %
b00000000000000000001000000010001 &
#500000000
b00000000000000000001000000000000 !
b00000000000000000000000000000001 "
b00000000000000000001000000000001 #
b00000000000000000001000000000000 $
b00000000000000000000000000000001 %
b00000000000000000001000000000001 &
#510000000
b00000000000000000000000100010001 "
b00000000000000000001000100010001 #
b00000000000000000000000100010001 %
b00000000000000000001000100010001 &
#520000000
b00000000000000000000000000000000 !
b00000000000000000000000000000001 "
b00000000000000000000000000000001 #
b00000000000000000000000000000000 $
b00000000000000000000000000000001 %
b00000000000000000000000000000001 &
#530000000
b00000000000000000000000000010000 !
b00000000000000000001000000000001 "
b00000000000000000001000000010001 #
b00000000000000000000000000010000 $
b00000000000000000001000000000001 %
b00000000000000000001000000010001 &
#540000000
b00000000000000000001000000000000 !
b00000000000000000000000000000001 "
b00000000000000000001000000000001 #
b00000000000000000001000000000000 $
b00000000000000000000000000000001 %
b00000000000000000001000000000001 &
#550000000
b00000000000000000000000100010001 "
b00000000000000000001000100010001 #
b00000000000000000000000100010001 %
b00000000000000000001000100010001 &
#560000000
b00000000000000000000000000000000 !
b00000000000000000000000000000001 "
b00000000000000000000000000000001 #
b00000000000000000000000000000000 $
b00000000000000000000000000000001 %
b00000000000000000000000000000001 &
#570000000
b00000000000000000000000000010000 !
b00000000000000000001000000000001 "
b00000000000000000001000000010001 #
b00000000000000000000000000010000 $
b00000000000000000001000000000001 %
b00000000000000000001000000010001 &
#580000000
b00000000000000000001000000000000 !
b00000000000000000000000000000001 "
b00000000000000000001000000000001 #
b00000000000000000001000000000000 $
b00000000000000000000000000000001 %
b00000000000000000001000000000001 &
#590000000
b00000000000000000000000100010001 "
b00000000000000000001000100010001 #
b00000000000000000000000100010001 %
b00000000000000000001000100010001 &
#600000000
b00000000000000000000000000000000 !
b00000000000000000000000000000001 "
b00000000000000000000000000000001 #
b00000000000000000000000000000000 $
b00000000000000000000000000000001 %
b00000000000000000000000000000001 &
