src/vhdl/PR2/REG.vhdl
library ieee;
use ieee.std_logic_1164.all;
use ieee.numeric_std.all;

entity REG is
generic(n: integer := 32);
port(
	DIN : in std_logic_vector(n-1 downto 0);
	RST : in std_logic;
	DOUT: out std_logic_vector(n-1 downto 0)
);
end entity;

architecture behavior of REG is
	signal data: std_logic_vector(n-1 downto 0) := (others=>'0');
begin

	process( DIN, RST ) begin
		if RST = '1' then
			data <= (others=>'0');
		else
			data <= DIN;
		end if;

		DOUT <= data;
	end process;

end architecture;

src/vhdl/PR2/tbs/TB_REG.vhdl
-- TIME=unknow
library ieee;
use ieee.std_logic_1164.all;
use ieee.numeric_std.all;

entity TB_REG is end entity;

architecture behavior of TB_REG is

	component REG is
	generic(n: integer := 32);
	port(
		DIN : in std_logic_vector(n-1 downto 0);
		RST : in std_logic;
		DOUT: out std_logic_vector(n-1 downto 0)
	);
	end component;

	signal din, dout: std_logic_vector(31 downto 0);
	signal rst: std_logic;

begin

	uut: REG
	generic map(n => 32)
	port map(
		DIN		=> din,
		RST 	=> rst,
		DOUT 	=> dout
	);


	Stimuli: process
		variable temp: unsigned(31 downto 0) := x"00000001";
	begin
		
		--	INITIALIZE
		rst <= '1';
		wait for 20 ns;
		rst <= '0';

		for i in 0 to 25 loop
			--	REAL PROCESS
			din <= std_logic_vector(temp);
			wait for 20 ns;

			-- SHIFT LEFT 1 BIT
			temp := temp sll 1;

			-- RESET
			if i = 10 then
				rst <= '1';
				wait for 20 ns;
				rst <= '0';
			end if ;
		end loop;

	end process;

end architecture;

src/vhdl/PR2/vcds/REG.vcd
$date
  Tue Jun 14 11:28:06 2022
$end
$version
  GHDL v0
$end
$timescale
  1 fs
$end
$scope module standard $end
$upscope $end
$scope module std_logic_1164 $end
$upscope $end
$scope module numeric_std $end
$upscope $end
$scope module tb_reg $end
$var reg 32 ! din[31:0] $end
$var reg 32 " dout[31:0] $end
$var reg 1 # rst $end
$scope module uut $end
$var reg 32 $ din[31:0] $end
$var reg 1 % rst $end
$var reg 32 & dout[31:0] $end
$var reg 32 ' data[31:0] $end
$upscope $end
$upscope $end
$enddefinitions $end
#0
bUUUUUUUUUUUUUUUUUUUUUUUUUUUUUUUU !
bUUUUUUUUUUUUUUUUUUUUUUUUUUUUUUUU "
1#
bUUUUUUUUUUUUUUUUUUUUUUUUUUUUUUUU $
1%
bUUUUUUUUUUUUUUUUUUUUUUUUUUUUUUUU &
b00000000000000000000000000000000 '
#20000000
b00000000000000000000000000000001 !
b00000000000000000000000000000000 "
0#
b00000000000000000000000000000001 $
0%
b00000000000000000000000000000000 &
b00000000000000000000000000000001 '
#40000000
b00000000000000000000000000000010 !
b00000000000000000000000000000001 "
b00000000000000000000000000000010 $
b00000000000000000000000000000001 &
b00000000000000000000000000000010 '
#60000000
b00000000000000000000000000000100 !
b00000000000000000000000000000010 "
b00000000000000000000000000000100 $
b00000000000000000000000000000010 &
b00000000000000000000000000000100 '
#80000000
b00000000000000000000000000001000 !
b00000000000000000000000000000100 "
b00000000000000000000000000001000 $
b00000000000000000000000000000100 &
b00000000000000000000000000001000 '
#100000000
b00000000000000000000000000010000 !
b00000000000000000000000000001000 "
b00000000000000000000000000010000 $
b00000000000000000000000000001000 &
b00000000000000000000000000010000 '
#120000000
b00000000000000000000000000100000 !
b00000000000000000000000000010000 "
b00000000000000000000000000100000 $
b00000000000000000000000000010000 &
b00000000000000000000000000100000 '
#140000000
b00000000000000000000000001000000 !
b00000000000000000000000000100000 "
b00000000000000000000000001000000 $
b00000000000000000000000000100000 &
b00000000000000000000000001000000 '
#160000000
b00000000000000000000000010000000 !
b00000000000000000000000001000000 "
b00000000000000000000000010000000 $
b00000000000000000000000001000000 &
b00000000000000000000000010000000 '
#180000000
b00000000000000000000000100000000 !
b00000000000000000000000010000000 "
b00000000000000000000000100000000 $
b00000000000000000000000010000000 &
b00000000000000000000000100000000 '
#200000000
b00000000000000000000001000000000 !
b00000000000000000000000100000000 "
b00000000000000000000001000000000 $
b00000000000000000000000100000000 &
b00000000000000000000001000000000 '
#220000000
b00000000000000000000010000000000 !
b00000000000000000000001000000000 "
b00000000000000000000010000000000 $
b00000000000000000000001000000000 &
b00000000000000000000010000000000 '
#240000000
b00000000000000000000010000000000 "
1#
1%
b00000000000000000000010000000000 &
b00000000000000000000000000000000 '
#260000000
b00000000000000000000100000000000 !
b00000000000000000000000000000000 "
0#
b00000000000000000000100000000000 $
0%
b00000000000000000000000000000000 &
b00000000000000000000100000000000 '
#280000000
b00000000000000000001000000000000 !
b00000000000000000000100000000000 "
b00000000000000000001000000000000 $
b00000000000000000000100000000000 &
b00000000000000000001000000000000 '
#300000000
b00000000000000000010000000000000 !
b00000000000000000001000000000000 "
b00000000000000000010000000000000 $
b00000000000000000001000000000000 &
b00000000000000000010000000000000 '
#320000000
b00000000000000000100000000000000 !
b00000000000000000010000000000000 "
b00000000000000000100000000000000 $
b00000000000000000010000000000000 &
b00000000000000000100000000000000 '
#340000000
b00000000000000001000000000000000 !
b00000000000000000100000000000000 "
b00000000000000001000000000000000 $
b00000000000000000100000000000000 &
b00000000000000001000000000000000 '
#360000000
b00000000000000010000000000000000 !
b00000000000000001000000000000000 "
b00000000000000010000000000000000 $
b00000000000000001000000000000000 &
b00000000000000010000000000000000 '
#380000000
b00000000000000100000000000000000 !
b00000000000000010000000000000000 "
b00000000000000100000000000000000 $
b00000000000000010000000000000000 &
b00000000000000100000000000000000 '
#400000000
b00000000000001000000000000000000 !
b00000000000000100000000000000000 "
b00000000000001000000000000000000 $
b00000000000000100000000000000000 &
b00000000000001000000000000000000 '
#420000000
b00000000000010000000000000000000 !
b00000000000001000000000000000000 "
b00000000000010000000000000000000 $
b00000000000001000000000000000000 &
b00000000000010000000000000000000 '
#440000000
b00000000000100000000000000000000 !
b00000000000010000000000000000000 "
b00000000000100000000000000000000 $
b00000000000010000000000000000000 &
b00000000000100000000000000000000 '
#460000000
b00000000001000000000000000000000 !
b00000000000100000000000000000000 "
b00000000001000000000000000000000 $
b00000000000100000000000000000000 &
b00000000001000000000000000000000 '
#480000000
b00000000010000000000000000000000 !
b00000000001000000000000000000000 "
b00000000010000000000000000000000 $
b00000000001000000000000000000000 &
b00000000010000000000000000000000 '
#500000000
b00000000100000000000000000000000 !
b00000000010000000000000000000000 "
b00000000100000000000000000000000 $
b00000000010000000000000000000000 &
b00000000100000000000000000000000 '
#520000000
b00000001000000000000000000000000 !
b00000000100000000000000000000000 "
b00000001000000000000000000000000 $
b00000000100000000000000000000000 &
b00000001000000000000000000000000 '
#540000000
b00000010000000000000000000000000 !
b00000001000000000000000000000000 "
b00000010000000000000000000000000 $
b00000001000000000000000000000000 &
b00000010000000000000000000000000 '
#560000000
b00000010000000000000000000000000 "
1#
1%
b00000010000000000000000000000000 &
b00000000000000000000000000000000 '
#580000000
b00000100000000000000000000000000 !
b00000000000000000000000000000000 "
0#
b00000100000000000000000000000000 $
0%
b00000000000000000000000000000000 &
b00000100000000000000000000000000 '
#600000000
b00001000000000000000000000000000 !
b00000100000000000000000000000000 "
b00001000000000000000000000000000 $
b00000100000000000000000000000000 &
b00001000000000000000000000000000 '
