src/vhdl/PR2/modules/SQUARE.vhdl
library ieee;
use ieee.std_logic_1164.all;
use ieee.numeric_std.all;

entity SQUARE is
generic(n: integer := 16);
port(
	A: in std_logic_vector(n-1 downto 0);
	R: out std_logic_vector((2*n-1) downto 0)
);
end entity;

architecture behavior of SQUARE is begin

	R <= std_logic_vector(resize(signed(A) * signed(A), 2*n));

end architecture;

src/vhdl/PR2/TB_SQUARE.vhdl
-- TIME=40ns
library ieee;
use ieee.std_logic_1164.all;

entity TB_SQUARE is end entity;

architecture behavior of TB_SQUARE is

	component SQUARE is
	generic(n: integer := 16);
	port(
		A: in std_logic_vector(n-1 downto 0);
		R: out std_logic_vector((2*n)-1 downto 0)
	);
	end component;

	signal a: std_logic_vector(15 downto 0);
	signal r: std_logic_vector(31 downto 0);

begin

	uut: SQUARE
	generic map(n => 16)
	port map(
		A 	=> a,
		R 	=> r
	);

	Stimuli: process begin
	
		a <= x"0002";
		wait for 10 ns;

		a <= x"0004";
		wait for 10 ns;

		a <= x"0008";
		wait for 10 ns;

		a <= x"0011";
		wait for 10 ns;

	end process;

end architecture;

src/vhdl/PR2/vcds/SQUARE.vcd
$date
  Tue Jun 14 11:28:13 2022
$end
$version
  GHDL v0
$end
$timescale
  1 fs
$end
$scope module standard $end
$upscope $end
$scope module std_logic_1164 $end
$upscope $end
$scope module numeric_std $end
$upscope $end
$scope module tb_square $end
$var reg 16 ! a[15:0] $end
$var reg 32 " r[31:0] $end
$scope module uut $end
$var reg 16 # a[15:0] $end
$var reg 32 $ r[31:0] $end
$upscope $end
$upscope $end
$enddefinitions $end
#0
b0000000000000010 !
b00000000000000000000000000000100 "
b0000000000000010 #
b00000000000000000000000000000100 $
#10000000
b0000000000000100 !
b00000000000000000000000000010000 "
b0000000000000100 #
b00000000000000000000000000010000 $
#20000000
b0000000000001000 !
b00000000000000000000000001000000 "
b0000000000001000 #
b00000000000000000000000001000000 $
#30000000
b0000000000010001 !
b00000000000000000000000100100001 "
b0000000000010001 #
b00000000000000000000000100100001 $
#40000000
b0000000000000010 !
b00000000000000000000000000000100 "
b0000000000000010 #
b00000000000000000000000000000100 $
#50000000
b0000000000000100 !
b00000000000000000000000000010000 "
b0000000000000100 #
b00000000000000000000000000010000 $
#60000000
b0000000000001000 !
b00000000000000000000000001000000 "
b0000000000001000 #
b00000000000000000000000001000000 $
#70000000
b0000000000010001 !
b00000000000000000000000100100001 "
b0000000000010001 #
b00000000000000000000000100100001 $
#80000000
b0000000000000010 !
b00000000000000000000000000000100 "
b0000000000000010 #
b00000000000000000000000000000100 $
#90000000
b0000000000000100 !
b00000000000000000000000000010000 "
b0000000000000100 #
b00000000000000000000000000010000 $
#100000000
b0000000000001000 !
b00000000000000000000000001000000 "
b0000000000001000 #
b00000000000000000000000001000000 $
#110000000
b0000000000010001 !
b00000000000000000000000100100001 "
b0000000000010001 #
b00000000000000000000000100100001 $
#120000000
b0000000000000010 !
b00000000000000000000000000000100 "
b0000000000000010 #
b00000000000000000000000000000100 $
#130000000
b0000000000000100 !
b00000000000000000000000000010000 "
b0000000000000100 #
b00000000000000000000000000010000 $
#140000000
b0000000000001000 !
b00000000000000000000000001000000 "
b0000000000001000 #
b00000000000000000000000001000000 $
#150000000
b0000000000010001 !
b00000000000000000000000100100001 "
b0000000000010001 #
b00000000000000000000000100100001 $
#160000000
b0000000000000010 !
b00000000000000000000000000000100 "
b0000000000000010 #
b00000000000000000000000000000100 $
#170000000
b0000000000000100 !
b00000000000000000000000000010000 "
b0000000000000100 #
b00000000000000000000000000010000 $
#180000000
b0000000000001000 !
b00000000000000000000000001000000 "
b0000000000001000 #
b00000000000000000000000001000000 $
#190000000
b0000000000010001 !
b00000000000000000000000100100001 "
b0000000000010001 #
b00000000000000000000000100100001 $
#200000000
b0000000000000010 !
b00000000000000000000000000000100 "
b0000000000000010 #
b00000000000000000000000000000100 $
#210000000
b0000000000000100 !
b00000000000000000000000000010000 "
b0000000000000100 #
b00000000000000000000000000010000 $
#220000000
b0000000000001000 !
b00000000000000000000000001000000 "
b0000000000001000 #
b00000000000000000000000001000000 $
#230000000
b0000000000010001 !
b00000000000000000000000100100001 "
b0000000000010001 #
b00000000000000000000000100100001 $
#240000000
b0000000000000010 !
b00000000000000000000000000000100 "
b0000000000000010 #
b00000000000000000000000000000100 $
#250000000
b0000000000000100 !
b00000000000000000000000000010000 "
b0000000000000100 #
b00000000000000000000000000010000 $
#260000000
b0000000000001000 !
b00000000000000000000000001000000 "
b0000000000001000 #
b00000000000000000000000001000000 $
#270000000
b0000000000010001 !
b00000000000000000000000100100001 "
b0000000000010001 #
b00000000000000000000000100100001 $
#280000000
b0000000000000010 !
b00000000000000000000000000000100 "
b0000000000000010 #
b00000000000000000000000000000100 $
#290000000
b0000000000000100 !
b00000000000000000000000000010000 "
b0000000000000100 #
b00000000000000000000000000010000 $
#300000000
b0000000000001000 !
b00000000000000000000000001000000 "
b0000000000001000 #
b00000000000000000000000001000000 $
#310000000
b0000000000010001 !
b00000000000000000000000100100001 "
b0000000000010001 #
b00000000000000000000000100100001 $
#320000000
b0000000000000010 !
b00000000000000000000000000000100 "
b0000000000000010 #
b00000000000000000000000000000100 $
#330000000
b0000000000000100 !
b00000000000000000000000000010000 "
b0000000000000100 #
b00000000000000000000000000010000 $
#340000000
b0000000000001000 !
b00000000000000000000000001000000 "
b0000000000001000 #
b00000000000000000000000001000000 $
#350000000
b0000000000010001 !
b00000000000000000000000100100001 "
b0000000000010001 #
b00000000000000000000000100100001 $
#360000000
b0000000000000010 !
b00000000000000000000000000000100 "
b0000000000000010 #
b00000000000000000000000000000100 $
#370000000
b0000000000000100 !
b00000000000000000000000000010000 "
b0000000000000100 #
b00000000000000000000000000010000 $
#380000000
b0000000000001000 !
b00000000000000000000000001000000 "
b0000000000001000 #
b00000000000000000000000001000000 $
#390000000
b0000000000010001 !
b00000000000000000000000100100001 "
b0000000000010001 #
b00000000000000000000000100100001 $
#400000000
b0000000000000010 !
b00000000000000000000000000000100 "
b0000000000000010 #
b00000000000000000000000000000100 $
#410000000
b0000000000000100 !
b00000000000000000000000000010000 "
b0000000000000100 #
b00000000000000000000000000010000 $
#420000000
b0000000000001000 !
b00000000000000000000000001000000 "
b0000000000001000 #
b00000000000000000000000001000000 $
#430000000
b0000000000010001 !
b00000000000000000000000100100001 "
b0000000000010001 #
b00000000000000000000000100100001 $
#440000000
b0000000000000010 !
b00000000000000000000000000000100 "
b0000000000000010 #
b00000000000000000000000000000100 $
#450000000
b0000000000000100 !
b00000000000000000000000000010000 "
b0000000000000100 #
b00000000000000000000000000010000 $
#460000000
b0000000000001000 !
b00000000000000000000000001000000 "
b0000000000001000 #
b00000000000000000000000001000000 $
#470000000
b0000000000010001 !
b00000000000000000000000100100001 "
b0000000000010001 #
b00000000000000000000000100100001 $
#480000000
b0000000000000010 !
b00000000000000000000000000000100 "
b0000000000000010 #
b00000000000000000000000000000100 $
#490000000
b0000000000000100 !
b00000000000000000000000000010000 "
b0000000000000100 #
b00000000000000000000000000010000 $
#500000000
b0000000000001000 !
b00000000000000000000000001000000 "
b0000000000001000 #
b00000000000000000000000001000000 $
#510000000
b0000000000010001 !
b00000000000000000000000100100001 "
b0000000000010001 #
b00000000000000000000000100100001 $
#520000000
b0000000000000010 !
b00000000000000000000000000000100 "
b0000000000000010 #
b00000000000000000000000000000100 $
#530000000
b0000000000000100 !
b00000000000000000000000000010000 "
b0000000000000100 #
b00000000000000000000000000010000 $
#540000000
b0000000000001000 !
b00000000000000000000000001000000 "
b0000000000001000 #
b00000000000000000000000001000000 $
#550000000
b0000000000010001 !
b00000000000000000000000100100001 "
b0000000000010001 #
b00000000000000000000000100100001 $
#560000000
b0000000000000010 !
b00000000000000000000000000000100 "
b0000000000000010 #
b00000000000000000000000000000100 $
#570000000
b0000000000000100 !
b00000000000000000000000000010000 "
b0000000000000100 #
b00000000000000000000000000010000 $
#580000000
b0000000000001000 !
b00000000000000000000000001000000 "
b0000000000001000 #
b00000000000000000000000001000000 $
#590000000
b0000000000010001 !
b00000000000000000000000100100001 "
b0000000000010001 #
b00000000000000000000000100100001 $
#600000000
b0000000000000010 !
b00000000000000000000000000000100 "
b0000000000000010 #
b00000000000000000000000000000100 $
